confo/Confo.py
confo/__init__.py
confo/Backends/AbstractBackend.py
confo/Backends/FileBackend.py
confo/Backends/ZookeeperBackend.py
confo/Backends/__init__.py
confo/Exceptions/__init__.py
confo-0.1.6.2.dist-info/LICENSE
confo-0.1.6.2.dist-info/METADATA
confo-0.1.6.2.dist-info/WHEEL
confo-0.1.6.2.dist-info/top_level.txt
confo-0.1.6.2.dist-info/RECORD
